<?xml version="1.0" encoding="UTF-8"?>


<categories>
<category name="Nerd Male">


	<skincolors>
		<skincolor>skin_kid_1</skincolor>
		<skincolor>skin_kid_2</skincolor>
		<skincolor>skin_kid_3</skincolor>
		<skincolor>skin_kid_4</skincolor>
	</skincolors>
	
	
	<heads>
		<head>kid_head_2</head> 
		<head>kid_head_3</head>
	</heads>
	
	
	<clothes> 
		<clothestype name="kid_clothes_1">
			<texture>clothes_kid1_blue</texture>
			<texture>clothes_kid1_green</texture>
			<texture>clothes_kid1_red</texture>
		</clothestype>
	</clothes>
	
	
	<accessories>
		<accessory name ="this could have been a watch if I was a decent programmer;)">
			<texture>not implemented in game yet huehue</texture>	
		</accessory>
	</accessories>
	
	
	<hairs>
		<hair name="dorky">
			<texture>hair_dorky_black</texture>
			<texture>hair_dorky_blonde</texture>
			<texture>hair_dorky_brown</texture>
			<texture>hair_dorky_red</texture>
		</hair> 
	</hairs>
	
	
	
	<preferenceTypes>
		<preferenceType>AMD64 assembly</preferenceType>
	</preferenceTypes>
	
	
	<preferenceAmounts>
		<preferenceAmount>64</preferenceAmount>
	</preferenceAmounts>
	
	
	<perfections>
		<perfection>0</perfection>
	</perfections>
	
	
	<patiences>
		<patience>9000</patience> 
	</patiences>
	
</category>


<category name="Grill Female">


	<skincolors>
		<skincolor>skin_kid_1</skincolor>
		<skincolor>skin_kid_2</skincolor>
		<skincolor>skin_kid_3</skincolor>
		<skincolor>skin_kid_4</skincolor>
	</skincolors>
	
	
	<heads>
		<head>kid_head_1</head> 
	</heads>
	
	
	<clothes> 
		<clothestype name="kid_clothes_2">
			<texture>clothes_kid2_blue</texture>
			<texture>clothes_kid2_green</texture>
			<texture>clothes_kid2_yellow</texture>
		</clothestype>
	</clothes>
	
	
	<accessories>
		<accessory name ="boomboom">
			<texture>for real</texture>	
		</accessory>
		<accessory name ="bambambam">
			<texture>umad johannes?</texture>
		</accessory>
	</accessories>
	
	
	<hairs>
		<hair name="pigtails">
			<texture>hair_pigtails_black</texture>
			<texture>hair_pigtails_blonde</texture>
			<texture>hair_pigtails_brown</texture>
			<texture>hair_pigtails_red</texture>
		</hair> 
		<hair name="ponytail">
			<texture>hair_ponytail_black</texture>
			<texture>hair_ponytail_blonde</texture>
			<texture>hair_ponytail_brown</texture>
			<texture>hair_ponytail_red</texture>
		</hair> 
	</hairs>
	
	
	
	<preferenceTypes>
		<preferenceType>Boisboisbois</preferenceType>
	</preferenceTypes>
	
	
	<preferenceAmounts>
		<preferenceAmount>1337</preferenceAmount>
	</preferenceAmounts>
	
	
	<perfections>
		<perfection>-5</perfection>
	</perfections>
	
	
	<patiences>
		<patience>404</patience> 
	</patiences>
	
</category>


</categories>